MANIFEST.in
requirements.txt
setup.cfg
setup.py
chirpy.egg-info/PKG-INFO
chirpy.egg-info/SOURCES.txt
chirpy.egg-info/dependency_links.txt
chirpy.egg-info/requires.txt
chirpy.egg-info/top_level.txt
scripts/chirpy
src/chirpy/__init__.py
src/chirpy/command_line.py
src/chirpy/configModule.py
src/chirpy/helpModule.py
src/chirpy/logModule.py
src/chirpy/parseModule.py
src/chirpy/profileModule.py
src/chirpy/searchModule.py
src/chirpy/streamModule.py
src/chirpy/streamer.py
src/chirpy/userModule.py