Metadata-Version: 1.1
Name: chirpy
Version: 1.0.6
Summary: chirpy is a command line interface for quickly collecting and parsing Twitter data.
Home-page: https://github.com/elric-dev/chirpy
Author: Haji Mohammad Saleem
Author-email: haji.saleem@mail.mcgill.ca
License: MIT
Keywords: twitter
Platform: UNKNOWN
Classifier: Development Status :: 2 - Pre-Alpha
Classifier: Intended Audience :: Science/Research
Classifier: Intended Audience :: System Administrators
Classifier: Intended Audience :: Information Technology
Classifier: Programming Language :: Python :: 2.7
Classifier: License :: OSI Approved :: MIT License
Classifier: Natural Language :: English
Classifier: Topic :: Internet
Classifier: Operating System :: MacOS
Classifier: Operating System :: Unix
